setup.py
pypiwik/__init__.py
pypiwik/api.py
pypiwik/server.py
pypiwik/user.py
pypiwik.egg-info/PKG-INFO
pypiwik.egg-info/SOURCES.txt
pypiwik.egg-info/dependency_links.txt
pypiwik.egg-info/top_level.txt