Metadata-Version: 1.1
Name: pypiwik
Version: 0.0.0dev
Summary: Python wrapper for the Piwik API
Home-page: http://github.com/pythagorists/pypiwik
Author: UNKNOWN
Author-email: UNKNOWN
License: MIT
Keywords: piwik
Platform: UNKNOWN
Classifier: Development Status :: 2 - Pre-Alpha
Classifier: Programming Language :: Python :: 2.6
Classifier: Programming Language :: Python :: 2.7
Classifier: Programming Language :: Python :: 3.3
Classifier: Programming Language :: Python :: 3.4
Classifier: Programming Language :: Python :: Implementation :: PyPy
Classifier: License :: OSI Approved :: MIT License
